{
  "resourceType": "StructureDefinition",
  "id": "ncdhc-observation-deworming",
  "url": "http://hl7.org.au/fhir/ch/v1/StructureDefinition/ncdhc-observation-deworming",
  "version": "r1.0.0",
  "name": "NCDHCDewormingObservationProfile",
  "title": "NCDHC Deworming Observation",
  "status": "draft",
  "date": "2019-02-01",
  "publisher": "National Children's Digital Health Collaborative (NCDHC)",
  "description": "To record if deworming is found",
  "purpose": "To record if deworming is found",
  "copyright": "Copyright © 2019 Australian Digital Health Agency - All rights reserved. This content is licensed under a Creative Commons Attribution 4.0 International License. See https://creativecommons.org/licenses/by/4.0/",
  "fhirVersion": "3.0.2",
  "kind": "resource",
  "abstract": false,
  "type": "Observation",
  "baseDefinition": "http://hl7.org.au/fhir/ch/v1/StructureDefinition/ncdhc-observation-base",
  "derivation": "constraint",
  "differential": {
    "element": [
      {
        "id": "Observation",
        "path": "Observation",
        "short": "NCDHC Deworming Observation Profile"
      },
      {
        "id": "Observation.category",
        "path": "Observation.category",
        "patternCodeableConcept": {
          "text": "This needs to be discussed and finalised"
        }
      },
      {
        "id": "Observation.code.coding",
        "path": "Observation.code.coding",
        "slicing": {
          "discriminator": [
            {
              "type": "pattern",
              "path": "code"
            },
            {
              "type": "value",
              "path": "system"
            }
          ],
          "rules": "open"
        }
      },
      {
        "id": "Observation.code.coding:DewormingSNOMED-CT",
        "path": "Observation.code.coding",
        "sliceName": "DewormingSNOMED-CT",
        "min": 1,
        "max": "1",
        "patternCoding": {
          "system": "http://snomed.info/sct",
          "code": "14369007"
        }
      },
      {
        "id": "Observation.code.coding:DewormingSNOMED-CT.system",
        "path": "Observation.code.coding.system",
        "min": 1,
        "fixedUri": "http://snomed.info/sct"
      },
      {
        "id": "Observation.code.coding:DewormingSNOMED-CT.code",
        "path": "Observation.code.coding.code",
        "min": 1
      },
      {
        "id": "Observation.subject",
        "path": "Observation.subject",
        "short": "Reference to the Baby Patient",
        "type": [
          {
            "code": "Reference",
            "targetProfile": "http://hl7.org.au/fhir/ch/v1/StructureDefinition/ncdhc-patient-baby"
          }
        ]
      },
      {
        "id": "Observation.effectiveDateTime:effectiveDateTime",
        "path": "Observation.effectiveDateTime",
        "sliceName": "effectiveDateTime",
        "short": "Date when Deworming was recorded"
      },
      {
        "id": "Observation.value[x]:valueCodeableConcept",
        "path": "Observation.valueCodeableConcept",
        "sliceName": "valueCodeableConcept",
        "type": [
          {
            "code": "CodeableConcept"
          }
        ],
        "mustSupport": true,
        "binding": {
          "strength": "required",
          "valueSetReference": {
            "reference": "http://hl7.org.au/fhir/ch/v1/ValueSet/ncdhc-observation-completion-status-1"
          }
        }
      },
      {
        "id": "Observation.interpretation",
        "path": "Observation.interpretation",
        "short": "Indication of whether a referral is needed. Allowed values are : Normal | Review | Refer. If the outcome of any of the component is \"Refer\" then, this will be changed to \"Refer\"",
        "binding": {
          "strength": "extensible",
          "valueSetReference": {
            "reference": "http://hl7.org.au/fhir/ch/v1/ValueSet/ncdhc-observation-interpretation-1"
          }
        }
      }
    ]
  }
}