{
    "resourceType": "Device",
    "id": "ncdhc-nsw-jt",
    "identifier": [
        {
            "type": {
                "coding": [
                    {
                        "system": "http://hl7.org.au/fhir/v2/0203",
                        "code": "NDI",
                        "display": "National Device Identifier"
                    }
                ],
                "text": "PAI-D"
            },
            "system": "http://ns.electronichealth.net.au/id/pcehr/paid/1.0",
            "value": "8003640003999995"
        }
    ],
    "meta": {
        "profile": [
            "http://hl7.org.au/fhir/StructureDefinition/au-device"
        ]
    },
    "text": {
        "status": "generated",
        "div": "<div xmlns=\"http://www.w3.org/1999/xhtml\">NCDHC JT</div>"
    },
    "udi": {
        "deviceIdentifier": "00844588003299",
        "name": "NCDHC JT"
    },
    "version": "v1.0.0",
    "status": "active",
    "owner": {
        "reference": "Organization/examiner-organization"
    },
    "contact": [
        {
            "system": "phone",
            "value": "0255554352"
        }
    ]
}